{
  "name": "Pin Matrix",
  "isInstrument": true,
  "explanation": "An eccentric British-modular mono/paraphonic synth instrument. Three free-running oscillators (saw, triangle, pulse) feed a ring modulator that multiplies two of them for clangy, inharmonic metallic tones, then a diode-ladder resonant low-pass that self-oscillates, all shaped by a snappy trapezoid-style envelope. Osc Mix crossfades saw against pulse over a triangle bed; Ring Mod sweeps in the bell-like inharmonic content; Cutoff and Resonance sweep and ring the filter toward self-oscillation; Env Amount and Decay drive the trapezoid's bite; pitch tracks the played note and the signal stays bounded by soft saturation.",
  "assembly": "factory/plugins/pin-matrix/assembly.ts",
  "out": "factory/plugins/pin-matrix/x.vstai",
  "guiFile": "factory/plugins/pin-matrix/gui.html",
  "publishedAt": 1751000097000,
  "theme": { "accent": "#6ad0ff", "accent2": "#ff7a7a" },
  "params": [
    { "name": "Osc Mix",    "index": 0, "min": 0, "max": 1, "default": 0.5 },
    { "name": "Ring Mod",    "index": 1, "min": 0, "max": 1, "default": 0.45 },
    { "name": "Cutoff",      "index": 2, "min": 0, "max": 1, "default": 0.5 },
    { "name": "Resonance",   "index": 3, "min": 0, "max": 1, "default": 0.55 },
    { "name": "Env Amount",  "index": 4, "min": 0, "max": 1, "default": 0.7 },
    { "name": "Decay",       "index": 5, "min": 0, "max": 1, "default": 0.45 },
    { "name": "Level",       "index": 6, "min": 0, "max": 1, "default": 0.7 }
  ]
}
